masonjar/__init__.py
masonjar/dictionary/__init__.py
masonjar/dictionary/dot.py
masonjar-0.1.0.dist-info/LICENSE
masonjar-0.1.0.dist-info/METADATA
masonjar-0.1.0.dist-info/WHEEL
masonjar-0.1.0.dist-info/top_level.txt
masonjar-0.1.0.dist-info/RECORD
