Metadata-Version: 2.1
Name: masonjar
Version: 0.1.0
Summary: Mason Jar is a collection of useful algorithms.
Home-page: https://docs.kuralabs.io/masonjar/
Author: KuraLabs S.R.L
Author-email: info@kuralabs.io
License: UNKNOWN
Keywords: masonjar
Platform: UNKNOWN
Classifier: Development Status :: 4 - Beta
Classifier: Intended Audience :: Developers
Classifier: License :: OSI Approved :: Apache Software License
Classifier: Natural Language :: English
Classifier: Operating System :: POSIX :: Linux
Classifier: Programming Language :: Python :: 3
